[
  {
    "studentName": "Gst 6",
    "timestamp": "2026-02-20T09:41:20.379Z",
    "status": "Pending",
    "answers": {
      "101": "c",
      "102": "c",
      "104": "b",
      "105": "b",
      "106": "b",
      "108": "a",
      "109": "b",
      "110": "a",
      "112": "a",
      "113": "c",
      "175": "a",
      "176": "b",
      "178": "b",
      "179": "b",
      "180": "b",
      "181": "a",
      "182": "c",
      "183": "a",
      "184": "a",
      "185": "a",
      "186": "a",
      "187": "c",
      "188": "c",
      "189": "b",
      "190": "a",
      "191": "b"
    },
    "currentQuestion": 14,
    "answeredCount": 26,
    "totalQuestions": 100,
    "questionFile": "GST-Model-Test-07.json"
  }
]